open3d_tools/__init__.py
open3d_tools/open3d_tools.py
open3d_tools-0.0.2.dist-info/LICENSE
open3d_tools-0.0.2.dist-info/METADATA
open3d_tools-0.0.2.dist-info/WHEEL
open3d_tools-0.0.2.dist-info/top_level.txt
open3d_tools-0.0.2.dist-info/RECORD
