Metadata-Version: 2.1
Name: open3d-tools
Version: 0.0.2
Summary: open3d tools
Home-page: https://github.com/lianghongzhuo/open3d_tools
Author: Hongzhuo Liang
Author-email: liang@informatik.uni-hamburg.de
License: MIT License
Platform: any
License-File: LICENSE
Requires-Dist: open3d
Requires-Dist: numpy
